{
  "project_info": {
    "project_number": "704041596135",
    "firebase_url": "https://mytiktok-62598.firebaseio.com",
    "project_id": "mytiktok-62598",
    "storage_bucket": "mytiktok-62598.appspot.com"
  },
  "client": [
    {
      "client_info": {
        "mobilesdk_app_id": "1:704041596135:android:37698370652ff2c5",
        "android_client_info": {
          "package_name": "com.photex.tiktok"
        }
      },
      "oauth_client": [
        {
          "client_id": "704041596135-m9goi3saht99s416tj33packjsgma26e.apps.googleusercontent.com",
          "client_type": 3
        }
      ],
      "api_key": [
        {
          "current_key": "AIzaSyBDo_msBop2w_vn2nobtamMfsL8ogs43GQ"
        }
      ],
      "services": {
        "analytics_service": {
          "status": 1
        },
        "appinvite_service": {
          "status": 1,
          "other_platform_oauth_client": []
        },
        "ads_service": {
          "status": 2
        }
      }
    }
  ],
  "configuration_version": "1"
}